{
    "root": {
        "next": {
            "price-value": {
                "next": {
                    "discount_rate": {
                        "next": {},
                        "keywords": [
                            "discounts",
                            "premium",
                            "price",
                            "coupon",
                            "deep_discount",
                            "value",
                            "offer_discounts",
                            "pricing",
                            "purchase",
                            "discounted_prices",
                            "slight_discount",
                            "discounted_rates",
                            "deeply_discounted",
                            "cheaper",
                            "sell",
                            "free",
                            "price",
                            "heavily_discounted",
                            "higher_priced",
                            "advertized_price",
                            "stock",
                            "discounting",
                            "prices",
                            "purchase_price",
                            "rebate",
                            "refund",
                            "purchases",
                            "pay",
                            "vouchers",
                            "inexpensive"
                        ]
                    }
                },
                "keywords": []
            },
            "overall": {
                "next": {
                    "cleanliness": {
                        "next": {},
                        "keywords": [
                            "hygiene",
                            "sanitary_conditions",
                            "sanitary",
                            "hygiene_standards",
                            "indoor_air",
                            "disinfecting",
                            "clean"
                        ]
                    },
                    "aesthetics": {
                        "next": {},
                        "keywords": [
                            "aesthetic",
                            "design",
                            "architecture",
                            "conceptual",
                            "wabi_sabi",
                            "geometry",
                            "geometric_forms",
                            "sculptural",
                            "creativity",
                            "style",
                            "midcentury",
                            "visual",
                            "art",
                            "artistic",
                            "sensibility",
                            "landscape",
                            "building",
                            "interior",
                            "art",
                            "piano",
                            "interior design",
                            "indoor",
                            "chandelier",
                            "luxury",
                            "ceiling",
                            "lobby",
                            "light",
                            "furniture",
                            "library",
                            "seat",
                            "decoration",
                            "wallpaper",
                            "illustration",
                            "palace",
                            "sculpture",
                            "zen",
                            "nature",
                            "wood",
                            "bamboo",
                            "outdoors",
                            "indoors",
                            "texture",
                            "antique",
                            "vintage",
                            "dirt",
                            "mud",
                            "material",
                            "traditional",
                            "decor"
                        ]
                    },
                    "safety": {
                        "next": {},
                        "keywords": [
                            "safety",
                            "safety_measures",
                            "safety_standards",
                            "safety_protocols",
                            "public_safety",
                            "safety_procedures",
                            "safety_concerns",
                            "safety_improvements",
                            "unsafe",
                            "security",
                            "safe",
                            "safety_requirements",
                            "safety_administration",
                            "emergency_exits",
                            "safeguarding",
                            "security_protocols",
                            "safely",
                            "protection",
                            "reliability",
                            "safety_precautions",
                            "precautions"
                        ]
                    },
                    "culture": {
                        "next": {},
                        "keywords": [
                            "loom",
                            "weaver",
                            "artisan",
                            "skill",
                            "thread",
                            "culture",
                            "religion",
                            "event",
                            "fame",
                            "wedding",
                            "music",
                            "art",
                            "colour",
                            "temple",
                            "church",
                            "buddhism",
                            "worship",
                            "culturally",
                            "spirituality",
                            "deeply_ingrained",
                            "notions",
                            "tolerance",
                            "stereotypes",
                            "norms",
                            "literature",
                            "cultural_influences",
                            "art_forms",
                            "popular_culture",
                            "values",
                            "youth_culture",
                            "moral_relativism",
                            "cultural_identity",
                            "consumerism",
                            "art_form",
                            "cultural_values",
                            "heritage",
                            "ideals",
                            "corporate_culture",
                            "diversity",
                            "morality",
                            "social",
                            "individualism",
                            "tradition",
                            "inclusivity",
                            "societies",
                            "cultural_diversity",
                            "ethic",
                            "attitudes",
                            "ethos",
                            "cultures",
                            "traditions",
                            "society",
                            "cultural"
                        ]
                    }
                },
                "keywords": []
            },
            "style": {
                "next": {
                    "boutique": {
                        "next": {},
                        "keywords": [
                            "boutiques",
                            "fivestory",
                            "boutique_style",
                            "trendy",
                            "upscale",
                            "chic",
                            "hostem",
                            "upmarket",
                            "sloane_street",
                            "stylish",
                            "vintage_furniture",
                            "firmdale",
                            "boutique_hotel",
                            "pastry_shops",
                            "luxurious",
                            "super_chic",
                            "vintage_clothing",
                            "vintage_shops",
                            "romantic",
                            "luxury"
                        ]
                    },
                    "classic": {
                        "next": {},
                        "keywords": [
                            "classics",
                            "vintage",
                            "retro",
                            "style",
                            "contemporary",
                            "iconic",
                            "famous",
                            "homage",
                            "inspired",
                            "featuring",
                            "timeless",
                            "legendary",
                            "quirky",
                            "reinterpreted",
                            "melds",
                            "reimagining",
                            "epic",
                            "whimsical",
                            "re_imagined",
                            "themed",
                            "mash_up",
                            "venerable",
                            "old_fashioned",
                            "features",
                            "elegant",
                            "americana",
                            "musical",
                            "noir",
                            "cinematic",
                            "quintessential",
                            "mixes"
                        ]
                    },
                    "family_friendly": {
                        "next": {},
                        "keywords": [
                            "kid_friendly",
                            "family_oriented",
                            "themed",
                            "waterslides",
                            "kiddie",
                            "theme_park",
                            "entertainment",
                            "dining_options",
                            "theme_parks",
                            "adult_themed",
                            "all_inclusive_resort",
                            "disney_world",
                            "themed_rides",
                            "kids'",
                            "offbeat",
                            "movie_screenings",
                            "musical_performances",
                            "dance_performances",
                            "walt_disney_world",
                            "jungle_themed",
                            "kids'_programming",
                            "wholesome",
                            "arcade_games",
                            "hayrides",
                            "friendly_amenities",
                            "kids'_activities",
                            "snallygaster",
                            "nature_trails",
                            "youth_oriented",
                            "amusement_park"
                        ]
                    }
                },
                "keywords": []
            },
            "services": {
                "next": {
                    "pre-room": {
                        "next": {
                            "pickup": {
                                "next": {},
                                "keywords": [
                                    "pickups",
                                    "toyota",
                                    "truck",
                                    "car",
                                    "chevrolet",
                                    "ford",
                                    "subaru",
                                    "driver",
                                    "dodge",
                                    "crew",
                                    "cab",
                                    "suv",
                                    "chrysler",
                                    "mini_van",
                                    "silverado",
                                    "nissan",
                                    "snow_plow",
                                    "gmc",
                                    "taxi",
                                    "drop_offs",
                                    "regular_cab",
                                    "vehicle",
                                    "trucks",
                                    "cadillac",
                                    "shuttle",
                                    "luggage"
                                ]
                            },
                            "welcome": {
                                "next": {},
                                "keywords": [
                                    "welcoming",
                                    "look_forward",
                                    "delighted",
                                    "invite",
                                    "warm_welcome",
                                    "greeted",
                                    "long_overdue",
                                    "pleased",
                                    "appreciative",
                                    "inviting",
                                    "enjoy",
                                    "invites",
                                    "warmly_welcomed",
                                    "applaud",
                                    "wholehearted",
                                    "heartening",
                                    "warmly_welcome",
                                    "good_afternoon",
                                    "good_evening",
                                    "thrilled",
                                    "grateful",
                                    "welcoming_visitors",
                                    "strive",
                                    "hospitality",
                                    "honoured",
                                    "gracious",
                                    "pleasant",
                                    "warm",
                                    "greeting",
                                    "hope",
                                    "fantastic",
                                    "memorable",
                                    "friendly",
                                    "appreciate",
                                    "thank"
                                ]
                            },
                            "reception_desk": {
                                "next": {},
                                "keywords": [
                                    "front_door",
                                    "front_desk",
                                    "doorway",
                                    "entrance",
                                    "vestibule",
                                    "door",
                                    "entryway",
                                    "conference_room",
                                    "phone_booth",
                                    "doors",
                                    "desk",
                                    "door",
                                    "doorbell",
                                    "gate",
                                    "bullet_proof_glass",
                                    "front_doors",
                                    "wood_panelled",
                                    "front_entrance",
                                    "front_gate",
                                    "doorknob",
                                    "desk_clerk",
                                    "booth",
                                    "mezzanine_level",
                                    "glass_enclosed",
                                    "wood_paneled",
                                    "elevator_doors"
                                ]
                            },
                            "checkin": {
                                "next": {},
                                "keywords": [
                                    "alloted",
                                    "check_in",
                                    "counter",
                                    "receptionist",
                                    "procedures",
                                    "concierge",
                                    "valet",
                                    "professional"
                                ]
                            }
                        },
                        "keywords": []
                    },
                    "in-room": {
                        "next": {
                            "housekeeping": {
                                "next": {},
                                "keywords": [
                                    "laundry",
                                    "cleaning",
                                    "mini_bar",
                                    "chores",
                                    "housekeepers",
                                    "janitorial",
                                    "cooking_cleaning",
                                    "valets",
                                    "tidying",
                                    "tomsky",
                                    "food_preparation",
                                    "scullery",
                                    "warm_dishes",
                                    "comforters",
                                    "accommodations",
                                    "child_care",
                                    "domestic_chores",
                                    "bedding",
                                    "preparing_meals",
                                    "laundry_facilities",
                                    "ironing",
                                    "washroom",
                                    "concierge_service",
                                    "valet_parking",
                                    "flushing_toilets",
                                    "rates_start",
                                    "diapers_changing",
                                    "babysitters",
                                    "household_tasks"
                                ]
                            },
                            "medical": {
                                "next": {},
                                "keywords": [
                                    "physicians",
                                    "doctors",
                                    "physician",
                                    "health",
                                    "clinical",
                                    "treatment",
                                    "patient",
                                    "patients",
                                    "medical_professionals",
                                    "psychiatric",
                                    "medical_care",
                                    "dental",
                                    "medicine"
                                ]
                            },
                            "laundry": {
                                "next": {},
                                "keywords": [
                                    "desk",
                                    "coin",
                                    "washer",
                                    "towels",
                                    "washing",
                                    "wash_dishes",
                                    "dishwasher",
                                    "laundry_room",
                                    "dryer",
                                    "wash",
                                    "dishwashing",
                                    "nappies",
                                    "toilet",
                                    "baby_wipes",
                                    "dirty_dishes",
                                    "linens",
                                    "dirty_clothes",
                                    "washing_machine",
                                    "liquid_detergent",
                                    "washrooms",
                                    "cleaning_supplies",
                                    "detergent",
                                    "washing_dishes",
                                    "doing_laundry",
                                    "kitchen_utencils"
                                ]
                            },
                            "general-service": {
                                "next": {},
                                "keywords": [
                                    "staff",
                                    "service"
                                ]
                            }
                        },
                        "keywords": []
                    },
                    "post-room": {
                        "next": {
                            "checkout": {
                                "next": {},
                                "keywords": [
                                    "formalities",
                                    "checkout",
                                    "reception",
                                    "taxi",
                                    "desk",
                                    "hassle",
                                    "check",
                                    "check-out",
                                    "12pm"
                                ]
                            }
                        },
                        "keywords": []
                    }
                },
                "keywords": []
            },
            "room": {
                "next": {
                    "furniture": {
                        "next": {},
                        "keywords": [
                            "bed",
                            "sofa",
                            "headboard",
                            "furniture",
                            "carpet",
                            "floor",
                            "interior",
                            "carpet",
                            "ceiling",
                            "indoor",
                            "mansion",
                            "rug",
                            "seat",
                            "wood",
                            "interior_design",
                            "shelf",
                            "table",
                            "desk"
                        ]
                    },
                    "appliances": {
                        "next": {},
                        "keywords": [
                            "lamp",
                            "television",
                            "refrigerator",
                            "fridge",
                            "microwave",
                            "mini_fridge",
                            "kettle",
                            "stockpot",
                            "electrical_appliances"
                        ]
                    },
                    "clothing": {
                        "next": {
                            "linens": {
                                "next": {},
                                "keywords": [
                                    "linen",
                                    "frette",
                                    "bedding",
                                    "egyptian_cotton",
                                    "bed_linens",
                                    "high_thread_count",
                                    "bed_linen",
                                    "smelly",
                                    "thread_count",
                                    "seets",
                                    "robe",
                                    "faboo",
                                    "bedspreads",
                                    "furnishings",
                                    "pillows",
                                    "towels",
                                    "molten_brown_toiletries",
                                    "table_linens",
                                    "pillow_menu",
                                    "tablecloths",
                                    "percale",
                                    "sheets",
                                    "sheets",
                                    "cotton_blend",
                                    "safari_tents",
                                    "comforters",
                                    "pillowcases",
                                    "robes",
                                    "bedspread"
                                ]
                            },
                            "curtains": {
                                "next": {},
                                "keywords": [
                                    "blinds",
                                    "window",
                                    "drapes",
                                    "walls",
                                    "carpet",
                                    "lights",
                                    "curtain",
                                    "windows",
                                    "pelmet",
                                    "damask",
                                    "heavy_drapes",
                                    "glass",
                                    "white_walls",
                                    "wallpaper",
                                    "frosted_glass",
                                    "fairy_lights",
                                    "upstairs",
                                    "white_tiled",
                                    "window_frames",
                                    "wooden_panels",
                                    "balcony",
                                    "lamps",
                                    "mosaic_tiles",
                                    "carpets",
                                    "floor"
                                ]
                            },
                            "bathrobe": {
                                "next": {},
                                "keywords": [
                                    "slippers",
                                    "kimonos",
                                    "robe",
                                    "paper",
                                    "towels",
                                    "robe",
                                    "pajamas",
                                    "dressing_gown",
                                    "sweat_pants",
                                    "shower_curtain",
                                    "underwear",
                                    "sweatpants",
                                    "nightdress",
                                    "pajama_pants",
                                    "nightgown"
                                ]
                            }
                        },
                        "keywords": []
                    },
                    "bathroom": {
                        "next": {
                            "bathtub": {
                                "next": {},
                                "keywords": [
                                    "bathroom",
                                    "tub",
                                    "bath",
                                    "bathtub_filled",
                                    "bedroom",
                                    "bed",
                                    "shower",
                                    "toilet",
                                    "bath_tub",
                                    "bathroom_sink",
                                    "master_bathroom",
                                    "apartment",
                                    "en_suite_bath",
                                    "kitchen_floor",
                                    "hotel_room_bathtub",
                                    "claw_foot",
                                    "floor",
                                    "marble_tiled",
                                    "shower_stall",
                                    "master_bath",
                                    "toilet_bowl",
                                    "backyard_swimming_pool",
                                    "commode",
                                    "whirlpool_tub"
                                ]
                            },
                            "shower": {
                                "next": {},
                                "keywords": [
                                    "showers",
                                    "bathroom",
                                    "toilet",
                                    "delousing",
                                    "bed",
                                    "shower_stall",
                                    "showerhead",
                                    "loo",
                                    "soaped",
                                    "showering",
                                    "washing",
                                    "shower_room",
                                    "soaping",
                                    "rain_shower",
                                    "bathing",
                                    "bath",
                                    "master_bath",
                                    "heated_floors",
                                    "whirlpool_tub",
                                    "bucket",
                                    "restroom",
                                    "cold_water",
                                    "room",
                                    "tub",
                                    "laundry",
                                    "steam_room",
                                    "jacuzzi",
                                    "bathtubs",
                                    "steam_bath",
                                    "soaking_tub",
                                    "lavatory",
                                    "baths"
                                ]
                            }
                        },
                        "keywords": []
                    }
                },
                "keywords": []
            },
            "food-beverages": {
                "next": {
                    "meal": {
                        "next": {
                            "vegetarian": {
                                "next": {},
                                "keywords": [
                                    "vegan_options",
                                    "vegetarians",
                                    "vegan",
                                    "meatless",
                                    "vegan_dishes",
                                    "vegetarian_food",
                                    "meals",
                                    "paneer",
                                    "raw_food",
                                    "veg",
                                    "veggie_burgers",
                                    "samosas",
                                    "pilaf",
                                    "vegetarian_options",
                                    "gluten_free",
                                    "aloo",
                                    "tandoori",
                                    "macrobiotic",
                                    "cooked",
                                    "veggie",
                                    "curries",
                                    "herbivoracious",
                                    "foodie",
                                    "vegetarianism",
                                    "pakora",
                                    "gluten_intolerant"
                                ]
                            },
                            "italian": {
                                "next": {},
                                "keywords": [
                                    "pasta",
                                    "garganelli",
                                    "rigatoni",
                                    "soup",
                                    "lasagna",
                                    "chitarra",
                                    "bolognese",
                                    "potpie",
                                    "beef_brisket",
                                    "farro",
                                    "pita",
                                    "lamb_stew",
                                    "parmigiana",
                                    "scampi",
                                    "orecchiette",
                                    "fresh_tomato_sauce",
                                    "oven_roasted",
                                    "chicken_salad",
                                    "vegetable_curry",
                                    "crabmeat",
                                    "meat_sauce",
                                    "carbonara",
                                    "ravioli",
                                    "vongole",
                                    "hard_boiled_eggs",
                                    "spaghetti_alla",
                                    "fettuccine",
                                    "pesto",
                                    "trofie",
                                    "braised_lamb",
                                    "parmigiano",
                                    "garlic_bread",
                                    "grilled_fish",
                                    "chicken_pot_pie",
                                    "angel_hair",
                                    "puttanesca"
                                ]
                            },
                            "thai": {
                                "next": {},
                                "keywords": [
                                    "mukda",
                                    "satay",
                                    "sour_sauce",
                                    "noodle_dish",
                                    "vegetable_dishes",
                                    "rice_noodles",
                                    "bananas_foster",
                                    "sticky_rice",
                                    "fried_oysters",
                                    "cocumber_salad",
                                    "tapas_style",
                                    "chicken_curry",
                                    "spicy",
                                    "steak_tartare",
                                    "vong",
                                    "izakaya",
                                    "chilli_sauce",
                                    "brown_shrimp",
                                    "scotch_egg",
                                    "fried_rice",
                                    "lettuce_wraps",
                                    "poblano",
                                    "lightly_spiced",
                                    "green_chicken_curry",
                                    "fish_soup",
                                    "sriracha",
                                    "green_papaya",
                                    "comfort_food",
                                    "chickpea",
                                    "roast_pork",
                                    "ikan",
                                    "pad_thai",
                                    "brochettes",
                                    "garlic_sauce"
                                ]
                            },
                            "french": {
                                "next": {},
                                "keywords": [
                                    "shallots",
                                    "wine",
                                    "vinegar",
                                    "tarragon",
                                    "olive",
                                    "mustard",
                                    "leeks",
                                    "herbes",
                                    "fleur_de_sel",
                                    "cheese",
                                    "butter",
                                    "breads"
                                ]
                            },
                            "breakfast": {
                                "next": {},
                                "keywords": [
                                    "breakfast",
                                    "cereals",
                                    "breads",
                                    "cuts",
                                    "fruits",
                                    "yoghurt",
                                    "coffee",
                                    "buffet",
                                    "eggs",
                                    "sausage",
                                    "bacon",
                                    "spread",
                                    "apple",
                                    "banana",
                                    "strawberry",
                                    "berry",
                                    "produce",
                                    "grape",
                                    "vegetable",
                                    "pot",
                                    "sauce"
                                ]
                            },
                            "seafood": {
                                "next": {},
                                "keywords": [
                                    "shellfish",
                                    "fresh_fish",
                                    "fish",
                                    "fresh_seafood",
                                    "locally_caught",
                                    "oysters",
                                    "prepared_foods",
                                    "food",
                                    "seafood_dishes",
                                    "seafood",
                                    "freshly_caught",
                                    "tuna",
                                    "red_snaper",
                                    "fish_tacos",
                                    "ceviche",
                                    "smoked_fish",
                                    "sushi_bars",
                                    "lobster",
                                    "shrimp",
                                    "seafood_restaurant",
                                    "salmon",
                                    "locally_sourced",
                                    "hamachi",
                                    "prawns",
                                    "oyster",
                                    "seafood_gumbo",
                                    "raw_tuna",
                                    "fried_fish",
                                    "raw_fish",
                                    "oyster_bar"
                                ]
                            }
                        },
                        "keywords": []
                    },
                    "food-decor": {
                        "next": {},
                        "keywords": [
                            "smell",
                            "assortment",
                            "culinary",
                            "gourmet",
                            "homemade",
                            "healthy"
                        ]
                    },
                    "drinks": {
                        "next": {},
                        "keywords": [
                            "drink",
                            "beer",
                            "cocktails",
                            "snacks",
                            "beverage",
                            "iced_teas",
                            "wine",
                            "bloody_mary",
                            "vodka",
                            "mojito",
                            "coffee",
                            "soda",
                            "soft_drinks",
                            "booze",
                            "fruit_juice",
                            "ounce_bottle",
                            "free_refills",
                            "mixed_drinks",
                            "smoothie",
                            "vitamin_water",
                            "milk",
                            "cup",
                            "porcelain",
                            "vase",
                            "jug"
                        ]
                    },
                    "restaurant": {
                        "next": {},
                        "keywords": [
                            "restaurant",
                            "lunch",
                            "dinner",
                            "chef",
                            "cooking",
                            "waiter",
                            "dining",
                            "cafe",
                            "indoor",
                            "service",
                            "restaurants",
                            "dining",
                            "cafe",
                            "bistro",
                            "menu",
                            "eatery",
                            "kitchen",
                            "italian_restaurant",
                            "dishes",
                            "tapas_bar",
                            "pizzeria",
                            "trattoria",
                            "oyster_bar",
                            "tapas_restaurant",
                            "michelin_starrred_restaurant",
                            "pizza",
                            "diners",
                            "bakery",
                            "food",
                            "osteria",
                            "thai_restaurant",
                            "seafood_restaurant",
                            "steakhouse"
                        ]
                    },
                    "bar": {
                        "next": {},
                        "keywords": [
                            "drinks",
                            "bars",
                            "lounge",
                            "cafe",
                            "pool",
                            "cocktails",
                            "room",
                            "evening",
                            "pub",
                            "cocktails",
                            "beach",
                            "lobby",
                            "beer",
                            "bistro",
                            "drink",
                            "cocktail_bar",
                            "poolside",
                            "terrace",
                            "glass"
                        ]
                    }
                },
                "keywords": []
            },
            "room-experience": {
                "next": {
                    "noise": {
                        "next": {},
                        "keywords": [
                            "noise",
                            "noisy",
                            "loud",
                            "quiet",
                            "crowded",
                            "busy"
                        ]
                    },
                    "view": {
                        "next": {},
                        "keywords": [
                            "room",
                            "view",
                            "balcony",
                            "hill"
                        ]
                    },
                    "privacy": {
                        "next": {},
                        "keywords": [
                            "privacy"
                        ]
                    },
                    "spacious": {
                        "next": {},
                        "keywords": [
                            "guest_rooms",
                            "marble_bathrooms",
                            "individually_decorated",
                            "mountain_views",
                            "colonial_style",
                            "four_poster_beds",
                            "outdoor_pool",
                            "chalet_style",
                            "seven_bedrooms",
                            "self_catering_apartments",
                            "minimalist_rooms",
                            "marble_floors",
                            "features_high_ceilings",
                            "high_ceilings",
                            "sun_deck",
                            "indoor_outdoor",
                            "lounge_bar",
                            "tropical_garden",
                            "pool_spa",
                            "room_boutique_hotel",
                            "outdoor_hot_tub",
                            "wood_burning_fireplaces",
                            "queen_beds",
                            "en_suite_bathrooms",
                            "private_baloconies",
                            "suites",
                            "gas_fireplace"
                        ]
                    }
                },
                "keywords": []
            },
            "amenities": {
                "next": {
                    "patio": {
                        "next": {},
                        "keywords": [
                            "landscape",
                            "lawn",
                            "yard",
                            "front",
                            "porch",
                            "veranda",
                            "outdoor_dining",
                            "terrace",
                            "dining_room",
                            "courtyard",
                            "picnic_tables",
                            "lounge",
                            "rooftop_deck",
                            "patio",
                            "roof_top",
                            "roof",
                            "top",
                            "fireplace",
                            "sliding_glass_doors",
                            "balcony",
                            "patios",
                            "french_doors",
                            "umbrella_shaded",
                            "outdoor_seating",
                            "pool",
                            "lounge",
                            "outdoor_shower",
                            "plunge_pool",
                            "bar",
                            "outdoor",
                            "roof_terrace",
                            "fire_pit",
                            "outdoor_space",
                            "dining",
                            "outdoor_dining",
                            "rooftop",
                            "picnic_tables",
                            "log_fire",
                            "private_terrace",
                            "roof_deck",
                            "outdoor_kitchen",
                            "outdoor_fireplace",
                            "upstairs",
                            "patio_doors"
                        ]
                    },
                    "garden": {
                        "next": {},
                        "keywords": [
                            "gazebo",
                            "flower",
                            "plant",
                            "garden",
                            "park",
                            "tree",
                            "shade",
                            "leaf",
                            "foliage",
                            "farm",
                            "soil",
                            "leaves",
                            "nature",
                            "grass",
                            "squirrel",
                            "frangipani",
                            "plumeria",
                            "floral",
                            "blossom",
                            "gardens",
                            "herbaceous_borders",
                            "kitchen_graden",
                            "raised_beds",
                            "herb_garden",
                            "herbaceous_border",
                            "glasshouse",
                            "lawn",
                            "vegetable_garden",
                            "orangery",
                            "walled_garden",
                            "pergola",
                            "hanging_baskets",
                            "flower_beds",
                            "acre_garden",
                            "trellises",
                            "summerhouse",
                            "gardening",
                            "gardens",
                            "flower_garden",
                            "formal_gardens",
                            "potting_shed",
                            "bamboos",
                            "botanical_garden",
                            "garden_designer",
                            "roof_garden",
                            "cottage",
                            "herbaceous_plans",
                            "cottage_garden",
                            "woodland",
                            "herb_gardens",
                            "wisley",
                            "rousham",
                            "rockery",
                            "succulents",
                            "garden",
                            "window_boxes",
                            "wild_flowers"
                        ]
                    },
                    "pool": {
                        "next": {
                            "swimming_pool": {
                                "next": {},
                                "keywords": [
                                    "turquoise",
                                    "canal",
                                    "lake",
                                    "river",
                                    "pool",
                                    "poolside",
                                    "swimming_pool",
                                    "swimming",
                                    "resort",
                                    "reflection",
                                    "lake",
                                    "river",
                                    "water",
                                    "duck",
                                    "pond",
                                    "fish"
                                ]
                            },
                            "infinity_pool": {
                                "next": {},
                                "keywords": [
                                    "plunge_pool",
                                    "sun_deck",
                                    "outdoor_pool",
                                    "rooftop_pool",
                                    "saltwater_pool",
                                    "white_sand_beach",
                                    "tropical_gardens",
                                    "stunning_views",
                                    "infinity_pools",
                                    "solarium",
                                    "private_terrace",
                                    "rooftop_terrace",
                                    "indoor_pool",
                                    "bedroom_villa",
                                    "outdoor_swimming_pool",
                                    "infinity_edge_pool",
                                    "heated_pool",
                                    "sauna_steam_room",
                                    "ocean_views",
                                    "infinity_edge",
                                    "casitas",
                                    "heated_outdoor_pool",
                                    "hot_tubs",
                                    "pleasure_palace",
                                    "white_sand_beaches",
                                    "terrace_overlooking",
                                    "white_sand",
                                    "hot_tub",
                                    "resort_spa"
                                ]
                            },
                            "spa": {
                                "next": {},
                                "keywords": [
                                    "resort",
                                    "massage",
                                    "pool",
                                    "sauna",
                                    "spa_treatments",
                                    "steam_bath",
                                    "spa_treatment",
                                    "hydrotherapy",
                                    "spa's",
                                    "square_foot_spa",
                                    "massages",
                                    "luxury_spa",
                                    "spa_facilities",
                                    "infinity_edge_pool",
                                    "outdoor_pool",
                                    "wellness_centre",
                                    "infinity_pool",
                                    "heated_outdoor_pool",
                                    "hot_tubs",
                                    "sauna_steam_room",
                                    "facials",
                                    "heated_indoor_pool"
                                ]
                            }
                        },
                        "keywords": []
                    },
                    "gym": {
                        "next": {},
                        "keywords": [
                            "equipments",
                            "train",
                            "carpet",
                            "steel",
                            "weights",
                            "cardio",
                            "workout",
                            "swimming",
                            "elliptical_machine",
                            "fitness",
                            "fitness_classes",
                            "gyms",
                            "lifting_weights",
                            "weights",
                            "boxercise",
                            "cardio-machines",
                            "treadmill",
                            "personal_trainer",
                            "fitness_routine",
                            "gym_sessions",
                            "spinning_classes",
                            "treadmills",
                            "indoor",
                            "room",
                            "fitness_centre",
                            "aerobic",
                            "rock_climbing_wall",
                            "professional",
                            "jogging",
                            "massage",
                            "lift_weights",
                            "pilates",
                            "bathroom",
                            "exercise_bike",
                            "rowing_machine",
                            "gym_equipment"
                        ]
                    },
                    "banquet": {
                        "next": {},
                        "keywords": [
                            "banquet",
                            "dining",
                            "tableware",
                            "carpet",
                            "reception",
                            "seat",
                            "theater",
                            "dinner",
                            "banquets",
                            "cocktail_reception",
                            "luncheon",
                            "gala-dinner",
                            "champagne_reception"
                        ]
                    },
                    "conference": {
                        "next": {},
                        "keywords": [
                            "education",
                            "group",
                            "table",
                            "school",
                            "desk",
                            "classroom",
                            "leader",
                            "discussion",
                            "meeting",
                            "indoor",
                            "furniture"
                        ]
                    },
                    "recreation": {
                        "next": {},
                        "keywords": [
                            "recreation",
                            "people",
                            "group",
                            "festival",
                            "audience",
                            "clothing",
                            "dancing",
                            "music",
                            "concert",
                            "dancer",
                            "performance",
                            "crowd",
                            "flag",
                            "wedding",
                            "band",
                            "drum",
                            "picnic",
                            "parks"
                        ]
                    },
                    "internet": {
                        "next": {},
                        "keywords": [
                            "internet",
                            "wifi",
                            "web",
                            "online",
                            "social_networks",
                            "social_media",
                            "websites",
                            "social_networking",
                            "web_sites",
                            "internet_users",
                            "social_networking_sites",
                            "facebook",
                            "facebook_twitter",
                            "content",
                            "users",
                            "internet's",
                            "mobile_devices",
                            "instant_messaging",
                            "google",
                            "social_network",
                            "mobile_phones",
                            "web_users",
                            "world_wide_web",
                            "social_media_sites",
                            "computers",
                            "networks",
                            "blogging_platform",
                            "web_based",
                            "web_giants",
                            "digital",
                            "social_media_platforms",
                            "file_sharing",
                            "internet_access",
                            "messaging_service",
                            "internet_connected",
                            "social_media_networks",
                            "user_generated_content",
                            "computer",
                            "streaming_video",
                            "youtube",
                            "user",
                            "mobile_internet"
                        ]
                    },
                    "elevator": {
                        "next": {},
                        "keywords": [
                            "elevators",
                            "stairs",
                            "floor",
                            "door",
                            "elevator_shaft",
                            "desk",
                            "bathroom",
                            "lobby",
                            "entrance",
                            "elevator_door",
                            "window",
                            "escalators",
                            "hallway",
                            "elevator_doors",
                            "manually_operated",
                            "upstairs",
                            "doormen",
                            "staircase",
                            "lifts"
                        ]
                    }
                },
                "keywords": []
            },
            "location": {
                "next": {
                    "sea": {
                        "next": {},
                        "keywords": [
                            "sunshine",
                            "summer",
                            "beach",
                            "idyllic",
                            "aqua",
                            "sand",
                            "nature",
                            "sun",
                            "tree",
                            "coastline",
                            "ocean",
                            "sea"
                        ]
                    },
                    "forest": {
                        "next": {},
                        "keywords": [
                            "tree",
                            "forest",
                            "wildlife",
                            "animal",
                            "fur",
                            "nut",
                            "monkey",
                            "lemur",
                            "zoo",
                            "avian",
                            "eagle"
                        ]
                    },
                    "mountains": {
                        "next": {},
                        "keywords": [
                            "mountain",
                            "hills",
                            "mountain_range",
                            "foothills",
                            "valleys"
                        ]
                    },
                    "airport": {
                        "next": {},
                        "keywords": [
                            "terminal",
                            "international_airport",
                            "flight",
                            "shuttle",
                            "bus"
                        ]
                    },
                    "station": {
                        "next": {},
                        "keywords": [
                            "metro",
                            "train",
                            "stations",
                            "bus",
                            "shuttle"
                        ]
                    },
                    "city_centre": {
                        "next": {},
                        "keywords": [
                            "walking_distance",
                            "walking",
                            "vicinity",
                            "touristy",
                            "town_centre",
                            "capital",
                            "shopping_centre",
                            "old_town",
                            "restaurants",
                            "shopping",
                            "shops",
                            "walkable",
                            "quaint",
                            "stroll",
                            "5/10min",
                            "up-and-coming",
                            "trendy_bars",
                            "souvenir_shops",
                            "bustling",
                            "emporiums",
                            "within_walking_distance",
                            "downtown",
                            "convenient",
                            "upscale_shops"
                        ]
                    }
                },
                "keywords": []
            },
            "hotel-outside": {
                "next": {
                    "activities": {
                        "next": {
                            "snorkeling": {
                                "next": {},
                                "keywords": [
                                    "snorkeling",
                                    "underwater",
                                    "diving",
                                    "chileno",
                                    "kayaking",
                                    "snorkel",
                                    "scuba_diving",
                                    "paros",
                                    "glass_bottomed_boat",
                                    "oahu_hawaii",
                                    "boat_rides",
                                    "tide_pools",
                                    "sea_kayaking",
                                    "rafting"
                                ]
                            },
                            "bike-ride": {
                                "next": {},
                                "keywords": [
                                    "bike",
                                    "ride",
                                    "town",
                                    "market",
                                    "bike-rides",
                                    "triathlon",
                                    "yomp",
                                    "jaunt",
                                    "mile_trek",
                                    "trek",
                                    "jog"
                                ]
                            },
                            "yoga": {
                                "next": {},
                                "keywords": [
                                    "yoga",
                                    "morning",
                                    "sunrise",
                                    "yoga_classes",
                                    "hatha",
                                    "ashtanga",
                                    "pilates",
                                    "vinyasa",
                                    "downward_dog",
                                    "asanas",
                                    "hatha_yoga",
                                    "pure_yoga",
                                    "hatha_yoga",
                                    "pure_yoga",
                                    "kundalini",
                                    "pilates_classes",
                                    "yoga_postures",
                                    "meditation_yoga",
                                    "bikram",
                                    "yoga_poses",
                                    "yoga_studios",
                                    "yogis",
                                    "breathing_techniques",
                                    "tantric",
                                    "yoga_studio",
                                    "ishta",
                                    "anusara",
                                    "yoga_classes",
                                    "meditation_classes",
                                    "fitness_classes",
                                    "transcendental_meditation",
                                    "mindfulness",
                                    "sivananda",
                                    "yogic",
                                    "meditation",
                                    "zumba",
                                    "tai_chi",
                                    "ashtanga_yoga",
                                    "jivamukti"
                                ]
                            },
                            "surfing": {
                                "next": {},
                                "keywords": [
                                    "surf",
                                    "surfers",
                                    "surfer",
                                    "paddle_boarding",
                                    "surf_school",
                                    "bodysurfing",
                                    "waterskiing",
                                    "surfs",
                                    "surfboards",
                                    "scuba_diving",
                                    "surf_lessons",
                                    "kayak",
                                    "kite_surfers",
                                    "kayaking",
                                    "surfboard",
                                    "longboard",
                                    "sea_kayaking",
                                    "bondi_beach",
                                    "riding",
                                    "windsurfers",
                                    "surf_city"
                                ]
                            },
                            "others": {
                                "next": {},
                                "keywords": [
                                    "tour",
                                    "adventure",
                                    "safari"
                                ]
                            }
                        },
                        "keywords": []
                    }
                },
                "keywords": []
            }
        },
        "keywords": []
    }
}